blue_firmament/__init__.py
blue_firmament/_types.py
blue_firmament/auth.py
blue_firmament/core/__init__.py
blue_firmament/core/app.py
blue_firmament/core/middleware.py
blue_firmament/dal/__init__.py
blue_firmament/dal/base.py
blue_firmament/dal/postgrest.py
blue_firmament/dal/query_components/__init__.py
blue_firmament/dal/query_components/filters.py
blue_firmament/dal/query_components/modifiers.py
blue_firmament/dal/query_components/operators.py
blue_firmament/dal/redis.py
blue_firmament/dal/types.py
blue_firmament/dal/utils.py
blue_firmament/data/settings/auth.py
blue_firmament/data/settings/base.py
blue_firmament/data/settings/dal.py
blue_firmament/data/settings/i18n.py
blue_firmament/data/settings/log.py
blue_firmament/dep_injc.py
blue_firmament/event.py
blue_firmament/exceptions.py
blue_firmament/log/__init__.py
blue_firmament/log/decorators.py
blue_firmament/log/main.py
blue_firmament/manager/__init__.py
blue_firmament/manager/base.py
blue_firmament/manager/common.py
blue_firmament/scheme/__init__.py
blue_firmament/scheme/business.py
blue_firmament/scheme/converter.py
blue_firmament/scheme/enum.py
blue_firmament/scheme/field.py
blue_firmament/scheme/main.py
blue_firmament/scheme/validator.py
blue_firmament/session/__init__.py
blue_firmament/session/base.py
blue_firmament/session/common.py
blue_firmament/setting.py
blue_firmament/task/__init__.py
blue_firmament/task/context/__init__.py
blue_firmament/task/context/common.py
blue_firmament/task/context/main.py
blue_firmament/task/handler.py
blue_firmament/task/main.py
blue_firmament/task/registry.py
blue_firmament/task/result.py
blue_firmament/transport/__init__.py
blue_firmament/transport/base.py
blue_firmament/transport/http/__init__.py
blue_firmament/transport/http/_types.py
blue_firmament/transport/http/base.py
blue_firmament/transport/http/main.py
blue_firmament/transport/pubsub.py
blue_firmament/transport/queue.py
blue_firmament/utils/__init__.py
blue_firmament/utils/auth_.py
blue_firmament-0.2.0.dist-info/LICENSE
blue_firmament-0.2.0.dist-info/METADATA
blue_firmament-0.2.0.dist-info/WHEEL
blue_firmament-0.2.0.dist-info/RECORD
