Metadata-Version: 2.3
Name: blue_firmament
Version: 0.2.0
Summary: A python backend framework
License: GNU General Public License v3 (GPLv3)
Author: Lan_zhijiang
Author-email: lanzhijiang@foxmail.com
Requires-Python: >=3.12
Classifier: Development Status :: 3 - Alpha
Classifier: Intended Audience :: Developers
Classifier: License :: OSI Approved :: GNU General Public License v3 (GPLv3)
Classifier: Natural Language :: Chinese (Simplified)
Classifier: Natural Language :: English
Classifier: Programming Language :: Python :: 3
Classifier: Programming Language :: Python :: 3.12
Classifier: Topic :: Software Development :: Libraries :: Python Modules
Provides-Extra: common
Provides-Extra: docs
Requires-Dist: black (>=25.1.0,<26.0.0)
Requires-Dist: doc8 (>=1.1.2) ; extra == "docs"
Requires-Dist: esbonio (>=0.12.0) ; extra == "docs"
Requires-Dist: nest-asyncio (>=1.6.0,<2.0.0)
Requires-Dist: postgrest (>=1.0.1,<2.0.0)
Requires-Dist: pyjwt (>=2.10.1,<3.0.0)
Requires-Dist: pytest (>=8.3.5,<9.0.0)
Requires-Dist: redis (>=6.2.0,<7.0.0) ; extra == "common"
Requires-Dist: setuptools (>=80.3.1,<81.0.0)
Requires-Dist: sphinx (>=4.0.0) ; extra == "docs"
Requires-Dist: sphinx-rtd-theme (>=1.0.0) ; extra == "docs"
Requires-Dist: structlog (>=25.3.0,<26.0.0)
Requires-Dist: supabase-auth (>=2.12.0,<3.0.0) ; extra == "common"
Requires-Dist: uvicorn (>=0.34.2,<0.35.0)
